{
  "railwayId": 1,
  "stations": {
    "1": "station01.json",
    "2": "station02.json",
    "3": "station03.json",
    "4": "station04.json",
    "5": "station05.json",
    "6": "station06.json",
    "7": "station07.json",
    "8": "station08.json",
    "9": "station09.json",
    "10": "station10.json",
    "11": "station11.json",
    "12": "station12.json",
    "13": "station13.json",
    "14": "station14.json",
    "15": "station15.json",
    "16": "station16.json",
    "17": "station17.json",
    "18": "station18.json",
    "20": "station20.json",
    "21": "station21.json",
    "22": "station22.json",
    "23": "station23.json",
    "24": "station24.json",
    "26": "station26.json",
    "29": "station29.json"
  }
}
